pydolphindb/__init__.py
pydolphindb/connection.py
pydolphindb/cursor.py
pydolphindb/exceptions.py
pydolphindb/helper.py
pydolphindb/sqlalchemy/__init__.py
pydolphindb/sqlalchemy/compiler.py
pydolphindb/sqlalchemy/custom_python_type.py
pydolphindb/sqlalchemy/dialect.py
pydolphindb/sqlalchemy/sa_version.py
pydolphindb/sqlalchemy/types.py
pydolphindb/superset/__init__.py
pydolphindb/superset/enginespec.py
pydolphindb/superset/utils.py
pydolphindb-1.1.2.dist-info/LICENSE
pydolphindb-1.1.2.dist-info/METADATA
pydolphindb-1.1.2.dist-info/WHEEL
pydolphindb-1.1.2.dist-info/entry_points.txt
pydolphindb-1.1.2.dist-info/top_level.txt
pydolphindb-1.1.2.dist-info/RECORD
