Metadata-Version: 2.1
Name: pydolphindb
Version: 1.1.2
Summary: A python DolphinDB API based on DBAPI2.0 Specification
Home-page: https://dolphindb.com
Author: DolphinDB, Inc.
Author-email: support@dolphindb.com
License: DolphinDB
Platform: any
Classifier: Operating System :: POSIX :: Linux
Classifier: Operating System :: Microsoft :: Windows
Classifier: Programming Language :: Python :: 3.7
Classifier: Programming Language :: Python :: 3.8
Classifier: Programming Language :: Python :: 3.9
Classifier: Programming Language :: Python :: 3.10
Classifier: Programming Language :: Python :: Implementation :: CPython
Requires-Python: >=3.7
License-File: LICENSE
Requires-Dist: dolphindb >=3.0.2.3
Requires-Dist: sqlalchemy <2.0,>=1.4
Requires-Dist: importlib-metadata >=0.23
